MANIFEST.in
README
setup.py
itunesnotify/__init__.py
itunesnotify/__main__.py
itunesnotify/cli.py
itunesnotify/core.py
itunesnotify/pid.txt
itunesnotify.egg-info/PKG-INFO
itunesnotify.egg-info/SOURCES.txt
itunesnotify.egg-info/dependency_links.txt
itunesnotify.egg-info/entry_points.txt
itunesnotify.egg-info/requires.txt
itunesnotify.egg-info/top_level.txt