Metadata-Version: 1.0
Name: itunesnotify
Version: 0.0.1.1
Summary: Providing song notifications for iTunes on Mac OSX
Home-page: https://github.com/Roasbeef/iTunes-Notify
Author: Olaoluwa Osuntokun
Author-email: laolu32@gmail.com
License: The Unlicense
Platform: UNKNOWN
